src/__init__.py
src/main.py
melonn_cli_project-0.1.3.dist-info/METADATA
melonn_cli_project-0.1.3.dist-info/WHEEL
melonn_cli_project-0.1.3.dist-info/entry_points.txt
melonn_cli_project-0.1.3.dist-info/top_level.txt
melonn_cli_project-0.1.3.dist-info/RECORD
