Metadata-Version: 2.2
Name: melonn-cli-project
Version: 0.1.3
Summary: CLI para la creación del proyecto completo
Author-email: Joaquin Mejia <nmejia@melonn.com>
Requires-Python: >=3.8
Requires-Dist: typer
Requires-Dist: aws-cdk-lib
